{
  "$type": "Anadarko.iMaps.DataTransfer.DTOTemplateDescription, Anadarko.iMaps.DataTransfer",
  "Filepath": null,
  "Width": 11.0,
  "Height": 17.0,
  "Legends": [
    {
      "$type": "Anadarko.iMaps.DataTransfer.DTOLegendDescription, Anadarko.iMaps.DataTransfer",
      "PageExtent": {
        "$type": "Anadarko.iMaps.DataTransfer.DTOEnvelope, Anadarko.iMaps.DataTransfer",
        "XMin": 0.58389999999963038,
        "YMin": 0.58410000000003492,
        "XMax": 1.27599999999984,
        "YMax": 0.80140000000028522
      },
      "Title": "Legend"
    }
  ],
  "TextElements": [
    {
      "$type": "Anadarko.iMaps.DataTransfer.DTONamedTextElementDescription, Anadarko.iMaps.DataTransfer",
      "Name": "dateQuikMap",
      "Text": "<DATETIME>"
    },
    {
      "$type": "Anadarko.iMaps.DataTransfer.DTONamedTextElementDescription, Anadarko.iMaps.DataTransfer",
      "Name": "GraphicText1",
      "Text": "Author:"
    },
    {
      "$type": "Anadarko.iMaps.DataTransfer.DTONamedTextElementDescription, Anadarko.iMaps.DataTransfer",
      "Name": "GraphicText2",
      "Text": "Date:"
    },
    {
      "$type": "Anadarko.iMaps.DataTransfer.DTONamedTextElementDescription, Anadarko.iMaps.DataTransfer",
      "Name": "GraphicText3",
      "Text": "Projection:"
    },
    {
      "$type": "Anadarko.iMaps.DataTransfer.DTONamedTextElementDescription, Anadarko.iMaps.DataTransfer",
      "Name": "GraphicText7",
      "Text": "Scale:"
    },
    {
      "$type": "Anadarko.iMaps.DataTransfer.DTONamedTextElementDescription, Anadarko.iMaps.DataTransfer",
      "Name": "prjQuikMap",
      "Text": "<PROJECTION>"
    },
    {
      "$type": "Anadarko.iMaps.DataTransfer.DTONamedTextElementDescription, Anadarko.iMaps.DataTransfer",
      "Name": "ttl1QuikMap",
      "Text": "<TITLE1>"
    },
    {
      "$type": "Anadarko.iMaps.DataTransfer.DTONamedTextElementDescription, Anadarko.iMaps.DataTransfer",
      "Name": "ttl2QuikMap",
      "Text": "<TITLE3>"
    }
  ],
  "MapFrames": [
    {
      "$type": "Anadarko.iMaps.DataTransfer.DTOMapFrameDescription, Anadarko.iMaps.DataTransfer",
      "PageExtent": {
        "$type": "Anadarko.iMaps.DataTransfer.DTOEnvelope, Anadarko.iMaps.DataTransfer",
        "XMin": 0.5,
        "YMin": 0.5,
        "XMax": 10.5,
        "YMax": 16.5
      },
      "MapExtent": {
        "$type": "Anadarko.iMaps.DataTransfer.DTOEnvelope, Anadarko.iMaps.DataTransfer",
        "XMin": -121.59407850304434,
        "YMin": 42.205861446319474,
        "XMax": -121.319522518645,
        "YMax": 42.645151021358416
      },
      "Name": "P11X17"
    }
  ]
}