{
  "$type": "Anadarko.iMaps.DataTransfer.DTOTemplateDescription, Anadarko.iMaps.DataTransfer",
  "Filepath": null,
  "Width": 34.0,
  "Height": 22.0,
  "Legends": [
    {
      "$type": "Anadarko.iMaps.DataTransfer.DTOLegendDescription, Anadarko.iMaps.DataTransfer",
      "PageExtent": {
        "$type": "Anadarko.iMaps.DataTransfer.DTOEnvelope, Anadarko.iMaps.DataTransfer",
        "XMin": 0.61440000000038708,
        "YMin": 0.61609999999927822,
        "XMax": 1.7996999999995751,
        "YMax": 0.98849999999947613
      },
      "Title": "Legend"
    }
  ],
  "TextElements": [
    {
      "$type": "Anadarko.iMaps.DataTransfer.DTONamedTextElementDescription, Anadarko.iMaps.DataTransfer",
      "Name": "dateQuikMap",
      "Text": "<DATETIME>"
    },
    {
      "$type": "Anadarko.iMaps.DataTransfer.DTONamedTextElementDescription, Anadarko.iMaps.DataTransfer",
      "Name": "GraphicText1",
      "Text": "Author:"
    },
    {
      "$type": "Anadarko.iMaps.DataTransfer.DTONamedTextElementDescription, Anadarko.iMaps.DataTransfer",
      "Name": "GraphicText2",
      "Text": "Date:"
    },
    {
      "$type": "Anadarko.iMaps.DataTransfer.DTONamedTextElementDescription, Anadarko.iMaps.DataTransfer",
      "Name": "GraphicText3",
      "Text": "Projection:"
    },
    {
      "$type": "Anadarko.iMaps.DataTransfer.DTONamedTextElementDescription, Anadarko.iMaps.DataTransfer",
      "Name": "GraphicText7",
      "Text": "Scale:"
    },
    {
      "$type": "Anadarko.iMaps.DataTransfer.DTONamedTextElementDescription, Anadarko.iMaps.DataTransfer",
      "Name": "prjQuikMap",
      "Text": "<PROJECTION>"
    },
    {
      "$type": "Anadarko.iMaps.DataTransfer.DTONamedTextElementDescription, Anadarko.iMaps.DataTransfer",
      "Name": "ttl1QuikMap",
      "Text": "<TITLE1>"
    },
    {
      "$type": "Anadarko.iMaps.DataTransfer.DTONamedTextElementDescription, Anadarko.iMaps.DataTransfer",
      "Name": "ttl2QuikMap",
      "Text": "<TITLE3>"
    }
  ],
  "MapFrames": [
    {
      "$type": "Anadarko.iMaps.DataTransfer.DTOMapFrameDescription, Anadarko.iMaps.DataTransfer",
      "PageExtent": {
        "$type": "Anadarko.iMaps.DataTransfer.DTOEnvelope, Anadarko.iMaps.DataTransfer",
        "XMin": 0.5,
        "YMin": 0.5,
        "XMax": 33.5,
        "YMax": 21.5
      },
      "MapExtent": {
        "$type": "Anadarko.iMaps.DataTransfer.DTOEnvelope, Anadarko.iMaps.DataTransfer",
        "XMin": -114.36463606888964,
        "YMin": 46.785620092649317,
        "XMax": -113.46006018978676,
        "YMax": 47.361259288442049
      },
      "Name": "L22X34"
    }
  ]
}